{
    "title": "Holidays",
    "description": "If there are still holidays left, this would be one of them. A rare moment to boost morale, but at what cost? Do we celebrate, or is survival the only thing that matters?",
    "options": [
      {
        "text": "Beck - We need this. A real celebration, a feast! For once, let’s forget the struggle and enjoy ourselves. The men deserve it, don't they?",
        "outcome": "The banquet lifts everyone's spirits. Laughter and warmth fill the air, but the supplies take a huge hit.",
        "effect": {
          "population": 0,
          "morale": 50,
          "foodWater": -200,
          "prosperity": 200,
          "energy": -100
        }
      },
      {
        "text": "Old-Timer - A little fun won’t kill us. Some games, music, and a small treat. We keep things controlled but still meaningful.",
        "outcome": "A modest gathering lifts spirits without breaking the bank. People feel refreshed, and resources remain stable.",
        "effect": {
          "population": 0,
          "morale": 20,
          "foodWater": -75,
          "prosperity": 0,
          "energy": -50
        }
      },
      {
        "text": "Shady - We’re alive, that’s enough. Bake a cake, share a few words, and move on. We can’t afford more than that.",
        "outcome": "A simple cake and a quiet reflection mark the occasion. It’s not much, but at least it’s something.",
        "effect": {
          "population": 0,
          "morale": 5,
          "foodWater": -20,
          "prosperity": 0,
          "energy": -10
        }
      }
    ]
  }
  